simple_resume/__init__.py
simple_resume/py.typed
simple_resume/core/__init__.py
simple_resume/core/colors.py
simple_resume/core/config.py
simple_resume/core/dependencies.py
simple_resume/core/effects.py
simple_resume/core/exceptions.py
simple_resume/core/file_operations.py
simple_resume/core/hydration.py
simple_resume/core/markdown.py
simple_resume/core/models.py
simple_resume/core/paths.py
simple_resume/core/protocols.py
simple_resume/core/py.typed
simple_resume/core/result.py
simple_resume/core/resume.py
simple_resume/core/skills.py
simple_resume/core/validation.py
simple_resume/core/ats/__init__.py
simple_resume/core/ats/base.py
simple_resume/core/ats/bert.py
simple_resume/core/ats/constants.py
simple_resume/core/ats/entities.py
simple_resume/core/ats/jaccard.py
simple_resume/core/ats/keyword.py
simple_resume/core/ats/reports.py
simple_resume/core/ats/tfidf.py
simple_resume/core/ats/tournament.py
simple_resume/core/constants/__init__.py
simple_resume/core/constants/colors.py
simple_resume/core/constants/files.py
simple_resume/core/constants/layout.py
simple_resume/core/generate/__init__.py
simple_resume/core/generate/exceptions.py
simple_resume/core/generate/html.py
simple_resume/core/generate/pdf.py
simple_resume/core/generate/plan.py
simple_resume/core/importers/__init__.py
simple_resume/core/importers/json_resume.py
simple_resume/core/latex/__init__.py
simple_resume/core/latex/context.py
simple_resume/core/latex/conversion.py
simple_resume/core/latex/escaping.py
simple_resume/core/latex/fonts.py
simple_resume/core/latex/formatting.py
simple_resume/core/latex/sections.py
simple_resume/core/latex/types.py
simple_resume/core/palettes/__init__.py
simple_resume/core/palettes/common.py
simple_resume/core/palettes/fetch_types.py
simple_resume/core/palettes/generators.py
simple_resume/core/palettes/registry.py
simple_resume/core/palettes/resolution.py
simple_resume/core/palettes/sources.py
simple_resume/core/palettes/data/default_palettes.json
simple_resume-0.2.2.dist-info/METADATA
simple_resume-0.2.2.dist-info/WHEEL
simple_resume-0.2.2.dist-info/entry_points.txt
simple_resume-0.2.2.dist-info/licenses/LICENSE
simple_resume-0.2.2.dist-info/RECORD
