Metadata-Version: 2.4
Name: simple-resume
Version: 0.2.2
Summary: Generate PDF resumes from YAML data using HTML templates
Author-email: Alex Thola <alexthola@gmail.com>
Maintainer-email: Alex Thola <alexthola@gmail.com>
License: MIT
License-File: LICENSE
Requires-Python: >=3.10
Requires-Dist: jinja2<4.0,>=3.0
Requires-Dist: markdown<4.0,>=3.7
Requires-Dist: oyaml<2.0,>=1.0
Requires-Dist: palettable<4.0,>=3.3.3
Requires-Dist: scikit-learn<2.0,>=1.5
Requires-Dist: weasyprint<63.0,>=62.1
Provides-Extra: bert
Requires-Dist: sentence-transformers<4.0,>=3.0; extra == 'bert'
Requires-Dist: torch<3.0,>=2.5; extra == 'bert'
Provides-Extra: utils
Requires-Dist: mypy<2.0,>=1.11.0; extra == 'utils'
Requires-Dist: pytest-cov<6.0,>=5.0.0; extra == 'utils'
Requires-Dist: pytest-mock<4.0,>=3.14.0; extra == 'utils'
Requires-Dist: pytest<9.0,>=8.3.3; extra == 'utils'
Requires-Dist: pytype>=2024.10.11; (python_version >= '3.10') and extra == 'utils'
Requires-Dist: ruff<1.0,>=0.7.0; extra == 'utils'
Requires-Dist: ty>=0.0.1a23; extra == 'utils'
Requires-Dist: types-markdown<4.0,>=3.7.2; extra == 'utils'
